nero_cli/__init__.py
nero_cli/__main__.py
nero_cli/__version__.py
nero_cli/cli.py
nero_cli-1.0.7.dist-info/METADATA
nero_cli-1.0.7.dist-info/WHEEL
nero_cli-1.0.7.dist-info/entry_points.txt
nero_cli-1.0.7.dist-info/licenses/LICENSE
nero_cli-1.0.7.dist-info/RECORD
