Metadata-Version: 2.3
Name: nero_cli
Version: 1.0.7
Summary: nero-cli is a simple CLI tool that streamlines the process of downloading Official InvokeAI release from github and running it on your local machine. It is designed to be a simple allow you to quickly and easily pull the latest version, specify version, or rollback if you need to.
Project-URL: Repository, https://github.com/regiellis/nero_cli
Project-URL: Documentation, https://github.com/regiellis/nero_cli/blob/main/README.md
Project-URL: Bug Tracker, https://github.com/regiellis/nero_cli/issues
Author-email: Regi Ellis <regi@bynine.io>
License: Copyright 2024 Regi E Ellis
Keywords: ai,cli,generative-ai,image,invokeai,tool,training
Classifier: License :: OSI Approved :: Apache Software License
Classifier: Operating System :: OS Independent
Classifier: Programming Language :: Python :: 3.10
Requires-Python: >=3.10
Requires-Dist: inquirer
Requires-Dist: packaging
